py7zz/7zz_version.txt
py7zz/__init__.py
py7zz/archive_info.py
py7zz/async_ops.py
py7zz/bundled_info.py
py7zz/callbacks.py
py7zz/cli.py
py7zz/compression.py
py7zz/config.py
py7zz/core.py
py7zz/detailed_parser.py
py7zz/exceptions.py
py7zz/filename_sanitizer.py
py7zz/logging_config.py
py7zz/security.py
py7zz/simple.py
py7zz/streaming.py
py7zz/thread_safe_config.py
py7zz/updater.py
py7zz/version.py
py7zz/bin/.gitkeep
py7zz/bin/7zz
LICENSE
THIRD_PARTY_NOTICES.md
LICENSES/LicenseRef-7zip.txt
py7zz-1.1.2.dist-info/METADATA
py7zz-1.1.2.dist-info/WHEEL
py7zz-1.1.2.dist-info/entry_points.txt
py7zz-1.1.2.dist-info/licenses/LICENSE
py7zz-1.1.2.dist-info/RECORD
