Metadata-Version: 2.4
Name: py7zz
Version: 1.1.2
Summary: Python wrapper for 7zz CLI tool providing cross-platform compression with multiple archive formats
Project-URL: Homepage, https://github.com/rxchi1d/py7zz
Project-URL: Issues, https://github.com/rxchi1d/py7zz/issues
Project-URL: Repository, https://github.com/rxchi1d/py7zz
Author: py7zz contributors
License: MIT License
License-File: LICENSE
Keywords: 7z,7zip,archive,compression
Classifier: Development Status :: 4 - Beta
Classifier: Intended Audience :: Developers
Classifier: License :: OSI Approved :: MIT License
Classifier: Operating System :: OS Independent
Classifier: Programming Language :: Python :: 3
Classifier: Programming Language :: Python :: 3.8
Classifier: Programming Language :: Python :: 3.9
Classifier: Programming Language :: Python :: 3.10
Classifier: Programming Language :: Python :: 3.11
Classifier: Programming Language :: Python :: 3.12
Classifier: Programming Language :: Python :: 3.13
Classifier: Topic :: Software Development :: Libraries :: Python Modules
Classifier: Topic :: System :: Archiving :: Compression
Requires-Python: >=3.8
Requires-Dist: packaging>=25.0
Requires-Dist: requests>=2.32.4
Requires-Dist: rich>=14.0.0
Requires-Dist: typer>=0.16.0
Provides-Extra: dev
